eye/__init__.py
eye/__main__.py
eye/app.py
eye/colorutils.py
eye/connector.py
eye/consts.py
eye/io.py
eye/lexers.py
eye/pathutils.py
eye/procutils.py
eye/qt.py
eye/reutils.py
eye/structs.py
eye/utils.py
eye/helpers/__init__.py
eye/helpers/_lexercolorgroups.py
eye/helpers/actions.py
eye/helpers/bookmarks.py
eye/helpers/buffers.py
eye/helpers/build.py
eye/helpers/build_annotations.py
eye/helpers/build_locationlist.py
eye/helpers/confcache.py
eye/helpers/editor_search.py
eye/helpers/elastictabstops.py
eye/helpers/file_monitor.py
eye/helpers/file_search.py
eye/helpers/focus_light.py
eye/helpers/folding.py
eye/helpers/intent.py
eye/helpers/keys.py
eye/helpers/lexer.py
eye/helpers/lexercolor.py
eye/helpers/macros.py
eye/helpers/margins.py
eye/helpers/minimap.py
eye/helpers/nav_history.py
eye/helpers/projects.py
eye/helpers/qt_all.py
eye/helpers/qt_doc.py
eye/helpers/quote_surround.py
eye/helpers/remote_control.py
eye/helpers/script_reload.py
eye/helpers/session.py
eye/helpers/styles.py
eye/helpers/welcome.py
eye/helpers/file_search_plugins/__init__.py
eye/helpers/file_search_plugins/base.py
eye/helpers/file_search_plugins/etags.py
eye/helpers/file_search_plugins/git.py
eye/helpers/file_search_plugins/grep.py
eye/helpers/ycm/__init__.py
eye/helpers/ycm/daemon.py
eye/helpers/ycm/extraconf.py
eye/helpers/ycm/feed.py
eye/helpers/ycm/query.py
eye/widgets/__init__.py
eye/widgets/dialog.py
eye/widgets/droparea.py
eye/widgets/editor.py
eye/widgets/eval_console.py
eye/widgets/filechooser.py
eye/widgets/helpers.py
eye/widgets/locationlist.py
eye/widgets/menus.py
eye/widgets/minibuffer.py
eye/widgets/misc.py
eye/widgets/search.py
eye/widgets/splitter.py
eye/widgets/tabs.py
eye/widgets/window.py
eyeditor-0.2.0.data/data/share/applications/eye.desktop
eyeditor-0.2.0.data/data/share/eye/colorschemes/solarized-dark.eyescheme
eyeditor-0.2.0.data/data/share/eye/colorschemes/solarized-light.eyescheme
eyeditor-0.2.0.data/data/share/eye/sample_conf/keyboard.ini
eyeditor-0.2.0.dist-info/COPYING.txt
eyeditor-0.2.0.dist-info/METADATA
eyeditor-0.2.0.dist-info/WHEEL
eyeditor-0.2.0.dist-info/entry_points.txt
eyeditor-0.2.0.dist-info/top_level.txt
eyeditor-0.2.0.dist-info/RECORD
