Metadata-Version: 2.1
Name: eyeditor
Version: 0.2.0
Summary: EYE - A Qt-based scriptable text editor
Home-page: https://github.com/hydrargyrum/eye
Author: Hg
Author-email: dev@indigo.re
License: WTFPL
Keywords: code,development,editor,qt,script,ide
Classifier: Development Status :: 3 - Alpha
Classifier: Environment :: X11 Applications :: Qt
Classifier: Intended Audience :: Developers
Classifier: Intended Audience :: System Administrators
Classifier: License :: Public Domain
Classifier: Topic :: Text Editors
Classifier: Topic :: Text Editors :: Integrated Development Environments (IDE)
Classifier: Programming Language :: Python :: 3
Classifier: Programming Language :: Python :: 3.4
Classifier: Programming Language :: Python :: 3.5
Classifier: Programming Language :: Python :: 3.6
Classifier: Programming Language :: Python :: 3.7
Classifier: Programming Language :: Python :: 3.8
Classifier: Programming Language :: Python :: 3.9
Requires-Python: >=3.3
License-File: COPYING.txt
Requires-Dist: PyQt5
Requires-Dist: QScintilla
Requires-Dist: pyxdg
